fastpt/FASTPT.py
fastpt/FASTPT_simple.py
fastpt/HT.py
fastpt/IA.py
fastpt/IA_ABD.py
fastpt/IA_ta.py
fastpt/IA_tt.py
fastpt/J_k.py
fastpt/J_table.py
fastpt/OV.py
fastpt/P_extend.py
fastpt/RG_RK4.py
fastpt/RG_RK4_filt.py
fastpt/RG_STS.py
fastpt/RG_ani.py
fastpt/RSD.py
fastpt/RSD_ItypeII.py
fastpt/Wigner_symbols.py
fastpt/__init__.py
fastpt/bias_choice_plot.py
fastpt/fastpt_extr.py
fastpt/filter_Pk.py
fastpt/gamma_funcs.py
fastpt/get_nu1_nu2.py
fastpt/info.py
fastpt/initialize_params.py
fastpt/kPol.py
fastpt/matter_power_spt.py
fastpt/param_matrix.py
fast_pt-3.2.dist-info/LICENSE
fast_pt-3.2.dist-info/METADATA
fast_pt-3.2.dist-info/WHEEL
fast_pt-3.2.dist-info/top_level.txt
fast_pt-3.2.dist-info/RECORD
