Metadata-Version: 2.1
Name: fast-pt
Version: 3.2
Summary: FAST-PT is a code to calculate quantities in cosmological perturbation theory at 1-loop (including, e.g., corrections to the matter power spectrum).
Author: Joseph E. McEwen, Xiao Fang, Jonathan Blazek
Author-email: blazek@berkeley.edu
License: MIT License
Project-URL: homepage, https://github.com/jablazek/FAST-PT
Keywords: FASTPT,FAST-PT,Perturbation-Theory
Classifier: Development Status :: 5 - Production/Stable
Classifier: Intended Audience :: Science/Research
Classifier: License :: OSI Approved :: MIT License
Classifier: Programming Language :: Python :: 3
Classifier: Topic :: Scientific/Engineering :: Astronomy
Classifier: Topic :: Scientific/Engineering :: Physics
Requires-Python: >=3.5
License-File: LICENSE
Requires-Dist: numpy>=1.17
Requires-Dist: scipy>=1.2
Requires-Dist: matplotlib>=3.0
